advanced_config_manager-1.0.dist-info/DESCRIPTION.rst
advanced_config_manager-1.0.dist-info/METADATA
advanced_config_manager-1.0.dist-info/metadata.json
advanced_config_manager-1.0.dist-info/RECORD
advanced_config_manager-1.0.dist-info/top_level.txt
advanced_config_manager-1.0.dist-info/WHEEL
AdvConfigMgr/advconfigmgr.py
AdvConfigMgr/config_exceptions.py
AdvConfigMgr/config_interpolation.py
AdvConfigMgr/config_migrate.py
AdvConfigMgr/config_ro_dict.py
AdvConfigMgr/config_storage.py
AdvConfigMgr/config_transform.py
AdvConfigMgr/config_types.py
AdvConfigMgr/config_validation.py
AdvConfigMgr/__init__.py
AdvConfigMgr/docs/conf.py
AdvConfigMgr/docs/__init__.py
AdvConfigMgr/tests/test_advanced_config.py
AdvConfigMgr/tests/test_adv_cfg_migrations.py
AdvConfigMgr/tests/test_adv_cfg_ro_dict.py
AdvConfigMgr/tests/test_adv_cfg_storage.py
AdvConfigMgr/tests/test_adv_cfg_transform.py
AdvConfigMgr/tests/test_adv_cfg_types.py
AdvConfigMgr/tests/__init__.py
AdvConfigMgr/utils/base_utils.py
AdvConfigMgr/utils/clicker_counter.py
AdvConfigMgr/utils/filehandler.py
AdvConfigMgr/utils/flag_manager.py
AdvConfigMgr/utils/indented_print.py
AdvConfigMgr/utils/unset.py
AdvConfigMgr/utils/version_range.py
AdvConfigMgr/utils/__init__.py
