Metadata-Version: 2.0
Name: advanced-config-manager
Version: 1.0
Summary: Advanced Configuration Manager
Home-page: http://advanced-config-manager.rtfd.org/
Author: Dan Strohl
Author-email: dan@wjcg.net
License: GNU GPL v2
Keywords: configuration INI database migration config setup plugin tool cli startup
Platform: UNKNOWN
Classifier: Development Status :: 2 - Pre-Alpha
Classifier: Environment :: Plugins
Classifier: Intended Audience :: Developers
Classifier: License :: OSI Approved :: GNU General Public License v2 (GPLv2)
Classifier: Natural Language :: English
Classifier: Operating System :: OS Independent
Classifier: Programming Language :: Python
Classifier: Topic :: Software Development :: Libraries :: Python Modules
Classifier: Topic :: Utilities
Requires-Dist: pathutils
